audio_tuner/__init__.py
audio_tuner/_namedpipe.py
audio_tuner/analysis.py
audio_tuner/argument_parser.py
audio_tuner/common.py
audio_tuner/error_handling.py
audio_tuner/tuning_systems.py
audio_tuner/scripts/__init__.py
audio_tuner/scripts/tuner.py
audio_tuner-0.10.0.dist-info/METADATA
audio_tuner-0.10.0.dist-info/WHEEL
audio_tuner-0.10.0.dist-info/entry_points.txt
audio_tuner-0.10.0.dist-info/licenses/COPYING
audio_tuner-0.10.0.dist-info/RECORD
