Metadata-Version: 2.4
Name: audio-tuner
Version: 0.10.0
Summary: Analyze the tuning of audio recordings
Project-URL: Homepage, https://codeberg.org/bluesloth/audio_tuner
Project-URL: Repository, https://codeberg.org/bluesloth/audio_tuner.git
Project-URL: Issues, https://codeberg.org/bluesloth/audio_tuner/issues
Project-URL: Documentation, https://audio-tuner.readthedocs.io/en/latest/
Author-email: Jessie Blue Cassell <bluesloth600@gmail.com>
License-File: COPYING
Keywords: audio,music,tuning
Classifier: License :: OSI Approved :: GNU General Public License v3 or later (GPLv3+)
Classifier: Operating System :: OS Independent
Classifier: Programming Language :: Python :: 3
Requires-Python: >=3.11
Requires-Dist: namedpipe; os_name != 'posix'
Requires-Dist: numpy
Requires-Dist: platformdirs
Requires-Dist: python-mpv
